tket/__init__.py
tket/_tket/__init__.pyi
tket/_tket/circuit.pyi
tket/_tket/ops.pyi
tket/_tket/optimiser.pyi
tket/_tket/passes.pyi
tket/_tket/pattern.pyi
tket/_tket/rewrite.pyi
tket/_tket/types.pyi
tket/_tket.abi3.so
tket/circuit/__init__.py
tket/circuit/build.py
tket/extensions/__init__.py
tket/ops.py
tket/optimiser.py
tket/passes.py
tket/pattern.py
tket/py.typed
tket/rewrite.py
tket/types.py
tket-0.12.15.dist-info/METADATA
tket-0.12.15.dist-info/WHEEL
tket-0.12.15.dist-info/licenses/LICENCE
tket.libs/libgcc_s-02f3f192.so.1
tket.libs/libm-f06f2ce1.so.6
tket.libs/libstdc++-a68762c8.so.6
tket.libs/libtket-c-api-5bbb125a.so
tket-0.12.15.dist-info/RECORD
