Metadata-Version: 2.4
Name: tket
Version: 0.12.15
Classifier: Environment :: Console
Classifier: Programming Language :: Python :: 3.10
Classifier: Programming Language :: Python :: 3.11
Classifier: Programming Language :: Python :: 3.12
Classifier: Programming Language :: Python :: 3.13
Classifier: Programming Language :: Python :: 3.14
Classifier: License :: OSI Approved :: Apache Software License
Classifier: Operating System :: MacOS :: MacOS X
Classifier: Operating System :: POSIX :: Linux
Classifier: Operating System :: Microsoft :: Windows
Classifier: Intended Audience :: Developers
Classifier: Intended Audience :: Science/Research
Classifier: Topic :: Scientific/Engineering
Requires-Dist: hugr~=0.15.0
Requires-Dist: pytket>=2.1.0,<3
Requires-Dist: tket-eccs~=0.5.1
Requires-Dist: tket-exts>=0.12.1,<0.13
License-File: LICENCE
Summary: Quantinuum's TKET Quantum Compiler
Home-Page: https://github.com/quantinuum/tket2
Author-email: TKET development team <tket-support@quantinuum.com>
Maintainer-email: TKET development team <tket-support@quantinuum.com>
Requires-Python: >=3.10
Project-URL: homepage, https://github.com/quantinuum/tket2/tree/main/tket-py
Project-URL: repository, https://github.com/quantinuum/tket2/tree/main/tket-py
